vitpose_infer/__init__.py
vitpose_infer/main.py
vitpose_infer/model_builder.py
vitpose_infer/setup.py
vitpose_infer/builder/__init__.py
vitpose_infer/builder/model_builder.py
vitpose_infer/builder/backbones/__init__.py
vitpose_infer/builder/backbones/alexnet.py
vitpose_infer/builder/backbones/cpm.py
vitpose_infer/builder/backbones/hourglass.py
vitpose_infer/builder/backbones/hourglass_ae.py
vitpose_infer/builder/backbones/hrformer.py
vitpose_infer/builder/backbones/litehrnet.py
vitpose_infer/builder/backbones/mobilenet_v2.py
vitpose_infer/builder/backbones/mobilenet_v3.py
vitpose_infer/builder/backbones/mspn.py
vitpose_infer/builder/backbones/regnet.py
vitpose_infer/builder/backbones/resnest.py
vitpose_infer/builder/backbones/resnext.py
vitpose_infer/builder/backbones/rsn.py
vitpose_infer/builder/backbones/scnet.py
vitpose_infer/builder/backbones/seresnet.py
vitpose_infer/builder/backbones/seresnext.py
vitpose_infer/builder/backbones/shufflenet_v1.py
vitpose_infer/builder/backbones/shufflenet_v2.py
vitpose_infer/builder/backbones/tcn.py
vitpose_infer/builder/backbones/test_torch.py
vitpose_infer/builder/backbones/vgg.py
vitpose_infer/builder/backbones/vipnas_mbv3.py
vitpose_infer/builder/backbones/vipnas_resnet.py
vitpose_infer/builder/backbones/vit.py
vitpose_infer/builder/backbones/utils/__init__.py
vitpose_infer/builder/backbones/utils/channel_shuffle.py
vitpose_infer/builder/backbones/utils/inverted_residual.py
vitpose_infer/builder/backbones/utils/make_divisible.py
vitpose_infer/builder/backbones/utils/se_layer.py
vitpose_infer/builder/backbones/utils/utils.py
vitpose_infer/builder/configs/coco/ViTPose_base_coco_256x192.py
vitpose_infer/builder/configs/coco/ViTPose_base_simple_coco_256x192.py
vitpose_infer/builder/configs/coco/ViTPose_huge_coco_256x192.py
vitpose_infer/builder/configs/coco/ViTPose_huge_simple_coco_256x192.py
vitpose_infer/builder/configs/coco/ViTPose_large_coco_256x192.py
vitpose_infer/builder/configs/coco/ViTPose_large_simple_coco_256x192.py
vitpose_infer-0.2.0.dist-info/LICENSE
vitpose_infer-0.2.0.dist-info/METADATA
vitpose_infer-0.2.0.dist-info/WHEEL
vitpose_infer-0.2.0.dist-info/top_level.txt
vitpose_infer-0.2.0.dist-info/RECORD
