Metadata-Version: 2.1
Name: vitpose_infer
Version: 0.2.0
Summary: Vitpose with yolov5 and tracking
Author-email: gpastal24 <some.email@gmail.com>
Project-URL: Homepage, https://github.com/gpastal24/ViTPose-Pytorch
Project-URL: Bug Tracker, https://github.com/gpastal24/ViTPose-Pytorch/issues
Classifier: Programming Language :: Python :: 3
Classifier: License :: OSI Approved :: MIT License
Classifier: Operating System :: OS Independent
Requires-Python: >=3.7
License-File: LICENSE
